{
    "word": "accepted",
    "type": [
        "adjective",
        "verb"
    ],
    "us": {
        "hasAudio": 1,
        "phoneticSpelling": [
            "/əkˈseptəd/",
            "/əkˈsɛptəd/"
        ]
    },
    "uk": {
        "hasAudio": 1,
        "phoneticSpelling": [
            "/əkˈsɛptɪd/"
        ]
    },
    "meanings": [
        {
            "content": "đã được công nhận",
            "type": "",
            "example": {}
        },
        {
            "content": "đã được thừa nhận",
            "type": "",
            "example": {}
        },
        {
            "content": "được công nhận",
            "type": "",
            "example": {
                "en": "Such confusion over commonly accepted values, however, has not stopped some people from searching for a moral code.",
                "vi": "Dù có nhiều quan điểm về những giá trị thường được công nhận, một số người vẫn tìm kiếm một tiêu chuẩn đạo đức."
            }
        }
    ]
}