{
    "word": "advertency",
    "type": [
        "noun"
    ],
    "us": {
        "hasAudio": 0,
        "phoneticSpelling": [
            "/ədˈvəːt(ə)nsi/"
        ]
    },
    "uk": {
        "hasAudio": 0,
        "phoneticSpelling": [
            "/ədˈvəːt(ə)nsi/"
        ]
    },
    "meanings": [
        {
            "content": "sự chú ý",
            "type": "",
            "example": {}
        },
        {
            "content": "sự lưu ý",
            "type": "",
            "example": {}
        }
    ]
}