{
    "word": "agglutinate",
    "type": "verb, adjective",
    "spelling": "",
    "meanings": [
        {
            "content": "dính kết",
            "type": "",
            "example": {
                "en": "No agglutination, no antibodies.",
                "vi": "Không thấy dính kết, không có kháng thể."
            }
        },
        {
            "content": "chấp dính",
            "type": "",
            "example": {}
        },
        {
            "content": "dán lại",
            "type": "",
            "example": {}
        },
        {
            "content": "hoá thành chất dính",
            "type": "",
            "example": {}
        },
        {
            "content": "làm dính",
            "type": "",
            "example": {}
        },
        {
            "content": "làm thành chất dính",
            "type": "",
            "example": {}
        }
    ],
    "hasAudio": 1
}