{
    "word": "air",
    "type": [
        "verb",
        "noun"
    ],
    "us": {
        "hasAudio": 1,
        "phoneticSpelling": [
            "/er/",
            "/ɛr/"
        ]
    },
    "uk": {
        "hasAudio": 1,
        "phoneticSpelling": [
            "/ɛː/"
        ]
    },
    "meanings": [
        {
            "content": "không khí",
            "type": "noun",
            "example": {
                "en": "She opened the window to let in fresh air.",
                "vi": "Cô mở cửa sổ để không khí trong lành ùa vào."
            }
        },
        {
            "content": "空氣",
            "type": "noun",
            "example": {}
        },
        {
            "content": "không trung",
            "type": "noun",
            "example": {
                "en": "She wrote poems and launched them into the air like birds.",
                "vi": "Bả làm thơ và thả nó vào không trung như những con chim."
            }
        },
        {
            "content": "hơi",
            "type": "noun",
            "example": {
                "en": "I'm gonna cut the air hoses, so stay close.",
                "vi": "Tôi sẽ cắt ống hơi, cho nên hãy ở sát nhau."
            }
        },
        {
            "content": "dáng",
            "type": "noun",
            "example": {
                "en": "I mean, come on, you were named most aerodynamic racer by Air Sports Illustrated.",
                "vi": "Ý tôi là, cục Hàng không công nhận cô là máy bay có dáng khí động học tốt."
            }
        },
        {
            "content": "dáng điệu",
            "type": "noun",
            "example": {}
        },
        {
            "content": "không",
            "type": "noun",
            "example": {
                "en": "She opened the window to let in fresh air.",
                "vi": "Cô mở cửa sổ để không khí trong lành ùa vào."
            }
        },
        {
            "content": "không gian",
            "type": "noun",
            "example": {
                "en": "As a kid, I was fascinated with all things air and space.",
                "vi": "Khi còn nhỏ, tôi rất thích thú với mọi điều về không gian và về vũ trụ"
            }
        },
        {
            "content": "khúc nhạc",
            "type": "",
            "example": {}
        },
        {
            "content": "dáng dấp",
            "type": "noun",
            "example": {}
        },
        {
            "content": "phơi gió",
            "type": "",
            "example": {}
        },
        {
            "content": "khí",
            "type": "noun",
            "example": {
                "en": "She opened the window to let in fresh air.",
                "vi": "Cô mở cửa sổ để không khí trong lành ùa vào."
            }
        },
        {
            "content": "gió",
            "type": "noun",
            "example": {
                "en": "I think at least a week before the winds cleanse the air.",
                "vi": "Tôi nghĩ ít nhất là một tuần trước khi gió đã làm sạch không khí."
            }
        },
        {
            "content": "vẻ",
            "type": "noun",
            "example": {
                "en": "Why is the air in here so negative?",
                "vi": "Sao ko khí ở đây có vẻ u ám thế?"
            }
        },
        {
            "content": "điệu",
            "type": "noun",
            "example": {
                "en": "I'll quickly play a short part of the air,",
                "vi": "Tôi nhanh chóng chơi một giai điệu quen thuộc,"
            }
        },
        {
            "content": "bầu không khí",
            "type": "",
            "example": {
                "en": "Hey, I'm gonna run downstairs for some fresh air.",
                "vi": "Tôi sẽ lên sân thượng để tận hưởng một bầu không khí trong lành nào đó."
            }
        },
        {
            "content": "bộ mặt",
            "type": "noun",
            "example": {}
        },
        {
            "content": "diện mạo",
            "type": "",
            "example": {}
        },
        {
            "content": "hàng không",
            "type": "noun",
            "example": {
                "en": "Tom tries to avoid traveling by air.",
                "vi": "Tom cố tránh di chuyển bằng đường hàng không."
            }
        },
        {
            "content": "khí sắc",
            "type": "noun",
            "example": {}
        },
        {
            "content": "khí trời",
            "type": "noun",
            "example": {
                "en": "And why did I bring helium instead of air?",
                "vi": "Và tại sao tôi lại mang bình thở helium thay vì khí trời."
            }
        },
        {
            "content": "khúc ca",
            "type": "",
            "example": {}
        },
        {
            "content": "làn gió nhẹ",
            "type": "",
            "example": {
                "en": "Into my heart, an air that kills... from yon far country blows.",
                "vi": "Từ trong lòng tôi, một làn gió nhẹ lấn át... những ngọn gió từ vùng hoang vu xa thẳm."
            }
        },
        {
            "content": "làn điệu",
            "type": "noun",
            "example": {}
        },
        {
            "content": "máy bay",
            "type": "noun",
            "example": {
                "en": "We have European passports, visas and air tickets.",
                "vi": "Vì chúng tôi có hộ chiếu châu Âu, có visa và vé máy bay."
            }
        },
        {
            "content": "nhạc khúc",
            "type": "",
            "example": {}
        },
        {
            "content": "thái độ",
            "type": "noun",
            "example": {
                "en": "Are you affected by this widespread “air,” or attitude?",
                "vi": "Bạn có bị ảnh hưởng bởi “không khí” hay thái độ phổ thông này không?"
            }
        },
        {
            "content": "vẻ ta đây",
            "type": "",
            "example": {
                "en": "Do they think I 'm putting on airs ?",
                "vi": "Họ có nghĩ rằng tôi làm ra vẻ ta đây ?"
            }
        },
        {
            "content": "điệu bộ màu mè",
            "type": "",
            "example": {}
        },
        {
            "content": "điệu ca",
            "type": "",
            "example": {}
        },
        {
            "content": "điệu nhạc",
            "type": "",
            "example": {
                "en": "The hum is music. The hum is light and air.",
                "vi": "Điệu nhạc là âm nhạc, là ánh sáng và không khí."
            }
        },
        {
            "content": "氣",
            "type": "",
            "example": {}
        },
        {
            "content": "Không khí",
            "type": "",
            "example": {
                "en": "Without air we would die.",
                "vi": "Không có không khí chúng ta sẽ chết."
            }
        }
    ]
}