{
    "word": "alleviative",
    "type": [
        "adjective",
        "noun"
    ],
    "uk": {
        "hasAudio": 1,
        "phoneticSpelling": [
            "/əˈliːvɪətɪv/"
        ]
    },
    "meanings": [
        {
            "content": "làm dịu",
            "type": "",
            "example": {
                "en": "These sedatives will alleviate your suffering during these final hours.",
                "vi": "Những viên thuốc an thần này sẽ làm dịu bớt đau đớn trong những giờ phút cuối cùng."
            }
        },
        {
            "content": "làm giảm đau",
            "type": "",
            "example": {
                "en": "If it's alleviating pain, who knows what else it's doing?",
                "vi": "Nếu nó làm giảm đau thì ai biết liệu nó còn gây ra cái gì nữa?"
            }
        },
        {
            "content": "làm khuây",
            "type": "",
            "example": {}
        }
    ]
}