{
    "word": "bacchus",
    "type": [
        "proper",
        "noun"
    ],
    "us": {
        "hasAudio": 1,
        "phoneticSpelling": [
            "/ˈbäkəs/",
            "/ˈbɑkəs/",
            "/ˈbakəs/",
            "/ˈbækəs/"
        ]
    },
    "uk": {
        "hasAudio": 1,
        "phoneticSpelling": [
            "/ˈbakəs/"
        ]
    },
    "meanings": [
        {
            "content": "thần rượu Bắc-cút",
            "type": "",
            "example": {}
        }
    ]
}