{
    "word": "blackfly",
    "type": [
        "noun"
    ],
    "uk": {
        "hasAudio": 1,
        "phoneticSpelling": [
            "/ˈblakflʌɪ/"
        ]
    },
    "meanings": [
        {
            "content": "giống rệp vừng",
            "type": "",
            "example": {}
        },
        {
            "content": "nhỏ màu đen",
            "type": "",
            "example": {}
        },
        {
            "content": "số nhiều blackflies",
            "type": "",
            "example": {}
        }
    ]
}