{
    "word": "blisteringly",
    "type": "adverb",
    "spelling": "",
    "meanings": [
        {
            "content": "cực kỳ",
            "type": "",
            "example": {}
        },
        {
            "content": "nghiêm khắc",
            "type": "adverb",
            "example": {}
        },
        {
            "content": "sắc bén",
            "type": "adverb",
            "example": {}
        },
        {
            "content": "vô cùng",
            "type": "adjective noun adverb",
            "example": {}
        }
    ],
    "hasAudio": 1
}