{
    "word": "boodle",
    "type": "noun",
    "spelling": "/ˈbuːdəl/",
    "meanings": [
        {
            "content": "lũ",
            "type": "",
            "example": {}
        },
        {
            "content": "đám",
            "type": "",
            "example": {}
        },
        {
            "content": "bọn",
            "type": "",
            "example": {}
        },
        {
            "content": "bài butđơ",
            "type": "",
            "example": {}
        },
        {
            "content": "quỹ đen",
            "type": "",
            "example": {}
        }
    ],
    "hasAudio": 1
}