{
    "word": "bulletproof",
    "type": [
        "adjective",
        "verb"
    ],
    "us": {
        "hasAudio": 1,
        "phoneticSpelling": [
            "/ˈbo͝olətˌpro͞of/",
            "/ˈbʊlətˌpruf/"
        ]
    },
    "uk": {
        "hasAudio": 1,
        "phoneticSpelling": [
            "/ˈbʊlɪtpruːf/"
        ]
    },
    "meanings": [
        {
            "content": "chống đạn",
            "type": "adjective",
            "example": {
                "en": "A bulletproof vest is a better investment than a crib.",
                "vi": "Xem ra áo chống đạn hợp lý hơn cái giỏ."
            }
        }
    ]
}