{
    "word": "caltrop",
    "type": [
        "noun"
    ],
    "us": {
        "hasAudio": 1,
        "phoneticSpelling": [
            "/ˈkaltrəp/",
            "/ˈkæltrəp/"
        ]
    },
    "uk": {
        "hasAudio": 1,
        "phoneticSpelling": [
            "/ˈkaltrəp/"
        ]
    },
    "meanings": [
        {
            "content": "cây củ ấu",
            "type": "",
            "example": {}
        },
        {
            "content": "củ ấu",
            "type": "noun",
            "example": {}
        }
    ]
}