{
    "word": "carboniferous",
    "type": [
        "adjective"
    ],
    "us": {
        "hasAudio": 1,
        "phoneticSpelling": [
            "/ˌkärbəˈnifərəs/",
            "/ˌkɑrbəˈnɪfərəs/"
        ]
    },
    "uk": {
        "hasAudio": 1,
        "phoneticSpelling": [
            "/ˌkɑːbəˈnɪf(ə)rəs/"
        ]
    },
    "meanings": [
        {
            "content": "chứa than",
            "type": "",
            "example": {}
        },
        {
            "content": "có than",
            "type": "",
            "example": {}
        },
        {
            "content": "hệ cacbon",
            "type": "",
            "example": {}
        },
        {
            "content": "kỷ than đá",
            "type": "",
            "example": {}
        }
    ]
}