{
    "word": "catholicism",
    "type": [
        "noun"
    ],
    "us": {
        "hasAudio": 1,
        "phoneticSpelling": [
            "/kəˈTHäləˌsizəm/",
            "/kəˈθɑləˌsɪzəm/"
        ]
    },
    "uk": {
        "hasAudio": 1,
        "phoneticSpelling": [
            "/kəˈθɒlɪsɪz(ə)m/"
        ]
    },
    "meanings": [
        {
            "content": "công giáo",
            "type": "noun",
            "example": {}
        },
        {
            "content": "đạo Thiên chúa",
            "type": "",
            "example": {}
        },
        {
            "content": "đạo thiên chúa",
            "type": "",
            "example": {}
        }
    ]
}