{
    "word": "cement",
    "type": [
        "verb",
        "noun"
    ],
    "us": {
        "hasAudio": 1,
        "phoneticSpelling": [
            "/səˈment/",
            "/səˈmɛnt/"
        ]
    },
    "uk": {
        "hasAudio": 1,
        "phoneticSpelling": [
            "/sɪˈmɛnt/"
        ]
    },
    "meanings": [
        {
            "content": "xi măng",
            "type": "noun",
            "example": {
                "en": "Decided to use recycled content from cement and steel manufacturing.",
                "vi": "Quyết định sử dụng thành phần tái chế từ ngành sản xuất xi măng và thép."
            }
        },
        {
            "content": "bột hàn răng",
            "type": "",
            "example": {}
        },
        {
            "content": "xương răng",
            "type": "",
            "example": {}
        },
        {
            "content": "hàn",
            "type": "",
            "example": {}
        },
        {
            "content": "bằng bột than",
            "type": "",
            "example": {}
        },
        {
            "content": "cho thấm cacbon ủ",
            "type": "",
            "example": {}
        },
        {
            "content": "chất gắn",
            "type": "",
            "example": {}
        },
        {
            "content": "gắn bó",
            "type": "",
            "example": {}
        },
        {
            "content": "mối gắn bó",
            "type": "",
            "example": {}
        },
        {
            "content": "mối liên kết",
            "type": "",
            "example": {}
        },
        {
            "content": "thắt chắc",
            "type": "",
            "example": {}
        },
        {
            "content": "trát xi-măng",
            "type": "",
            "example": {}
        },
        {
            "content": "xi-măng",
            "type": "noun",
            "example": {
                "en": "That cement's the only thing between us and a blowout.",
                "vi": "Chỗ xi măng đó là thứ duy nhất chắn giữa chúng ta và một vụ nổ dầu."
            }
        },
        {
            "content": "xây bằng xi-măng",
            "type": "",
            "example": {}
        },
        {
            "content": "Xi măng",
            "type": "",
            "example": {
                "en": "That cement's the only thing between us and a blowout.",
                "vi": "Chỗ xi măng đó là thứ duy nhất chắn giữa chúng ta và một vụ nổ dầu."
            }
        }
    ]
}