{
    "word": "commission",
    "type": [
        "verb",
        "noun"
    ],
    "us": {
        "hasAudio": 1,
        "phoneticSpelling": [
            "/kəˈmiSHən/",
            "/kəˈmɪʃən/"
        ]
    },
    "uk": {
        "hasAudio": 1,
        "phoneticSpelling": [
            "/kəˈmɪʃ(ə)n/"
        ]
    },
    "meanings": [
        {
            "content": "hoa hồng",
            "type": "noun",
            "example": {
                "en": "I don't know if it's Brill's price that's goir up or your commission.",
                "vi": "Không biết đó là Brill tăng hay tiền hoa hồng của cô?"
            }
        },
        {
            "content": "tiền hoa hồng",
            "type": "noun",
            "example": {
                "en": "I don't know if it's Brill's price that's goir up or your commission.",
                "vi": "Không biết đó là Brill tăng hay tiền hoa hồng của cô?"
            }
        },
        {
            "content": "nhiệm vụ",
            "type": "noun",
            "example": {
                "en": "He has been commissioned to care for us.",
                "vi": "Ngài được giao nhiệm vụ chăm sóc chúng ta."
            }
        },
        {
            "content": "lệnh",
            "type": "noun",
            "example": {
                "en": "And we got a commission to design a building",
                "vi": "Và chúng tôi được lệnh phải thiết kế một kiến trúc"
            }
        },
        {
            "content": "ban",
            "type": "noun",
            "example": {
                "en": "He's a framer for one of my latest commissions.",
                "vi": "Cậu ấy là nông dân cho một trong những ủy ban của ta."
            }
        },
        {
            "content": "công việc uỷ nhiệm",
            "type": "",
            "example": {}
        },
        {
            "content": "công việc uỷ thác",
            "type": "",
            "example": {}
        },
        {
            "content": "hội đồng uỷ ban",
            "type": "",
            "example": {}
        },
        {
            "content": "mệnh lệnh",
            "type": "",
            "example": {
                "en": "Do health inspectors work on commission?",
                "vi": "Các thanh tra y tế chỉ làm việc theo mệnh lệnh?"
            }
        },
        {
            "content": "phận sự",
            "type": "",
            "example": {}
        },
        {
            "content": "sự can phạm",
            "type": "",
            "example": {}
        },
        {
            "content": "sự phạm",
            "type": "",
            "example": {
                "en": "The defense then presented three witnesses, none of whom had seen its commission.",
                "vi": "Rồi luật sư của bị cáo trình diện ba nhân chứng, không một ai trong số họ đã trông thấy sự phạm tội."
            }
        },
        {
            "content": "sự uỷ nhiệm",
            "type": "",
            "example": {}
        },
        {
            "content": "sự uỷ thác",
            "type": "",
            "example": {}
        },
        {
            "content": "uỷ nhiệm",
            "type": "",
            "example": {}
        },
        {
            "content": "uỷ thác",
            "type": "",
            "example": {
                "en": "Because you're going to commission everything you bring in.",
                "vi": "Vì anh sẽ uỷ thác tất cả mọi thứ đưa vào."
            }
        },
        {
            "content": "đặt làm",
            "type": "",
            "example": {}
        },
        {
            "content": "đặt mua",
            "type": "",
            "example": {}
        },
        {
            "content": "ủy ban",
            "type": "noun",
            "example": {
                "en": "He's a framer for one of my latest commissions.",
                "vi": "Cậu ấy là nông dân cho một trong những ủy ban của ta."
            }
        },
        {
            "content": "uỷ",
            "type": "",
            "example": {
                "en": "Because you're going to commission everything you bring in.",
                "vi": "Vì anh sẽ uỷ thác tất cả mọi thứ đưa vào."
            }
        },
        {
            "content": "hội đồng",
            "type": "noun",
            "example": {
                "en": "My ship will sail long before the commission even sits.",
                "vi": "Tàu của tôi sẽ ra khơi trước khi hội đồng ngồi lại."
            }
        },
        {
            "content": "tieàn hoa hoàng",
            "type": "",
            "example": {}
        }
    ]
}