{
    "word": "connoisseur",
    "type": [
        "noun"
    ],
    "us": {
        "hasAudio": 1,
        "phoneticSpelling": [
            "/ˌkänəˈsər/",
            "/ˌkɑnəˈsər/",
            "/ˌkänəˈso͝or/",
            "/ˌkɑnəˈsʊr/"
        ]
    },
    "uk": {
        "hasAudio": 1,
        "phoneticSpelling": [
            "/ˌkɒnəˈsəː/"
        ]
    },
    "meanings": [
        {
            "content": "người sành sỏi",
            "type": "",
            "example": {
                "en": "It's a connoisseur's reaction of delight,",
                "vi": "Phản ứng vui mừng của một người sành sỏi,"
            }
        },
        {
            "content": "người thành thạo",
            "type": "",
            "example": {}
        },
        {
            "content": "người am hiểu",
            "type": "",
            "example": {
                "en": "I'm a connoisseur when it comes to eau de toilette.",
                "vi": "Tôi là một người am hiểu khi nói đến nước dội bồn cầu."
            }
        },
        {
            "content": "người sành điệu",
            "type": "",
            "example": {
                "en": "I can see you are a connoisseur in all things.",
                "vi": "Tôi thấy ông đúng là người sành điệu."
            }
        }
    ]
}