{
    "word": "cramp",
    "type": [
        "verb",
        "noun"
    ],
    "us": {
        "hasAudio": 1,
        "phoneticSpelling": [
            "/kramp/",
            "/kræmp/"
        ]
    },
    "uk": {
        "hasAudio": 1,
        "phoneticSpelling": [
            "/kramp/"
        ]
    },
    "meanings": [
        {
            "content": "chuột rút",
            "type": "noun",
            "example": {
                "en": "Fibroids can cause severe cramps and heavier bleeding during your period .",
                "vi": "U xơ có thể gây chuột rút dữ dội và xuất huyết nhiều hơn trong kỳ kinh ."
            }
        },
        {
            "content": "bàn kẹp mộng",
            "type": "",
            "example": {}
        },
        {
            "content": "bị chuột rút",
            "type": "",
            "example": {
                "en": "You may have cramps for several days after the miscarriage .",
                "vi": "Bạn có thể bị chuột rút nhiều ngày sau khi sẩy thai ."
            }
        },
        {
            "content": "chứng ruột rút",
            "type": "",
            "example": {}
        },
        {
            "content": "khó đọc",
            "type": "",
            "example": {}
        },
        {
            "content": "kẹp bằng bàn kẹp",
            "type": "",
            "example": {}
        },
        {
            "content": "kẹp bằng thanh kẹp",
            "type": "",
            "example": {}
        },
        {
            "content": "làm cho co gân",
            "type": "",
            "example": {}
        },
        {
            "content": "sự bó buộc",
            "type": "",
            "example": {}
        },
        {
            "content": "sự câu thúc",
            "type": "",
            "example": {}
        },
        {
            "content": "sự gò bó",
            "type": "",
            "example": {}
        },
        {
            "content": "sự tù túng",
            "type": "",
            "example": {}
        },
        {
            "content": "vọp bẻ",
            "type": "noun",
            "example": {
                "en": "I will get a cramp and sink like a stone.",
                "vi": "Em sẽ bị vọp bẻ và chìm như một tảng đá."
            }
        },
        {
            "content": "Chuột rút",
            "type": "",
            "example": {
                "en": "Fibroids can cause severe cramps and heavier bleeding during your period .",
                "vi": "U xơ có thể gây chuột rút dữ dội và xuất huyết nhiều hơn trong kỳ kinh ."
            }
        },
        {
            "content": "cản trở",
            "type": "",
            "example": {
                "en": "I still think you're cramping my style.",
                "vi": "Tôi vẫn nghĩ là bà cản trở phong cách của tôi."
            }
        }
    ]
}