{
    "word": "defecation",
    "type": [
        "noun"
    ],
    "us": {
        "hasAudio": 1,
        "phoneticSpelling": [
            "/ˌdefəˈkāSHən/",
            "/ˌdɛfəˈkeɪʃən/"
        ]
    },
    "uk": {
        "hasAudio": 1,
        "phoneticSpelling": [
            "/ˌdɛfɪˈkeɪʃ(ə)n/"
        ]
    },
    "meanings": [
        {
            "content": "sự làm trong",
            "type": "",
            "example": {}
        },
        {
            "content": "sự gạn",
            "type": "",
            "example": {}
        },
        {
            "content": "sự lọc",
            "type": "",
            "example": {}
        },
        {
            "content": "sự đi tiêu",
            "type": "",
            "example": {}
        },
        {
            "content": "sự đi ỉa",
            "type": "",
            "example": {}
        },
        {
            "content": "tiêu",
            "type": "noun",
            "example": {
                "en": "and a lot of it is because of open defecation.",
                "vi": "và nhiều trường hợp là vì đi tiêu lộ thiên."
            }
        },
        {
            "content": "Đại tiện",
            "type": "",
            "example": {
                "en": "and going over to the open defecating ground.",
                "vi": "để rồi lại đi đại tiện ngoài đường."
            }
        },
        {
            "content": "đại tiện",
            "type": "",
            "example": {
                "en": "and going over to the open defecating ground.",
                "vi": "để rồi lại đi đại tiện ngoài đường."
            }
        }
    ]
}