{
    "word": "disastrously",
    "type": [
        "adverb"
    ],
    "us": {
        "hasAudio": 1,
        "phoneticSpelling": [
            "/dəˈzastrəslē/",
            "/dəˈzæstrəsli/"
        ]
    },
    "uk": {
        "hasAudio": 1,
        "phoneticSpelling": [
            "/dɪˈzɑːstrəsli/"
        ]
    },
    "meanings": [
        {
            "content": "thảm họa",
            "type": "",
            "example": {
                "en": "One of the very first human decisions on record was disastrous.",
                "vi": "Chính một trong những quyết định đầu tiên của họ trong sử sách đã đem lại thảm họa."
            }
        }
    ]
}