{
    "word": "disgusted",
    "type": [
        "adjective",
        "verb"
    ],
    "us": {
        "hasAudio": 1,
        "phoneticSpelling": [
            "/disˈɡəstəd/",
            "/dɪsˈɡəstəd/"
        ]
    },
    "uk": {
        "hasAudio": 1,
        "phoneticSpelling": [
            "/dɪsˈɡʌstɪd/"
        ]
    },
    "meanings": [
        {
            "content": "cảm thấy ghê tởm",
            "type": "adjective",
            "example": {
                "en": "that some people are easier to disgust than others.",
                "vi": "một số người thì dễ cảm thấy ghê tởm về một cái gì đó hơn những người khác."
            }
        }
    ]
}