{
    "word": "dissatisfactory",
    "type": [
        "adjective"
    ],
    "uk": {
        "hasAudio": 0,
        "phoneticSpelling": [
            "/-ˈfakt(ə)ri/"
        ]
    },
    "meanings": [
        {
            "content": "không làm bằng lòng",
            "type": "",
            "example": {}
        },
        {
            "content": "không làm hài lòng",
            "type": "",
            "example": {}
        },
        {
            "content": "không làm thoả mãn",
            "type": "",
            "example": {}
        },
        {
            "content": "làm bất mãn",
            "type": "",
            "example": {}
        }
    ]
}