{
    "word": "donnybrook",
    "type": [
        "noun"
    ],
    "us": {
        "hasAudio": 1,
        "phoneticSpelling": [
            "/ˈdänēˌbro͝ok/",
            "/ˈdɑniˌbrʊk/"
        ]
    },
    "uk": {
        "hasAudio": 1,
        "phoneticSpelling": [
            "/ˈdɒnɪbrʊk/"
        ]
    },
    "meanings": [
        {
            "content": "cuộc loạn đả",
            "type": "",
            "example": {}
        },
        {
            "content": "cuộc ẩu đả",
            "type": "",
            "example": {}
        },
        {
            "content": "cảnh huyên náo",
            "type": "",
            "example": {}
        }
    ]
}