{
    "word": "eyesore",
    "type": [
        "noun"
    ],
    "us": {
        "hasAudio": 1,
        "phoneticSpelling": [
            "/ˈīsôr/",
            "/ˈaɪsɔr/"
        ]
    },
    "uk": {
        "hasAudio": 1,
        "phoneticSpelling": [
            "/ˈʌɪsɔː/"
        ]
    },
    "meanings": [
        {
            "content": "điều chướng mắt",
            "type": "",
            "example": {}
        },
        {
            "content": "vật chướng mắt",
            "type": "",
            "example": {}
        }
    ]
}