{
    "word": "failure",
    "type": [
        "noun"
    ],
    "us": {
        "hasAudio": 1,
        "phoneticSpelling": [
            "/ˈfālyər/",
            "/ˈfeɪljər/"
        ]
    },
    "uk": {
        "hasAudio": 1,
        "phoneticSpelling": [
            "/ˈfeɪljə/"
        ]
    },
    "meanings": [
        {
            "content": "sự thất bại",
            "type": "noun",
            "example": {
                "en": "His failure has nothing to do with me.",
                "vi": "Sự thất bại của anh ấy không có liên quan gì tới tôi."
            }
        },
        {
            "content": "hư hỏng",
            "type": "",
            "example": {
                "en": "Computer, display these failures over time.",
                "vi": "Máy tính, hiển thị những hư hỏng theo thời gian."
            }
        },
        {
            "content": "người bị thất bại",
            "type": "",
            "example": {}
        },
        {
            "content": "sự hỏng",
            "type": "noun",
            "example": {
                "en": "There can never be a mechanical or electronic failure when we pray.",
                "vi": "Không bao giờ có thể có sự hỏng máy hay điện tử khi chúng ta cầu nguyện."
            }
        },
        {
            "content": "sự không làm được",
            "type": "",
            "example": {}
        },
        {
            "content": "sự không xảy ra",
            "type": "",
            "example": {}
        },
        {
            "content": "sự mất",
            "type": "",
            "example": {}
        },
        {
            "content": "sự phá sản",
            "type": "",
            "example": {}
        },
        {
            "content": "sự thi hỏng",
            "type": "",
            "example": {}
        },
        {
            "content": "sự thiếu",
            "type": "",
            "example": {}
        },
        {
            "content": "sự vỡ nợ",
            "type": "",
            "example": {}
        },
        {
            "content": "thất bại",
            "type": "noun",
            "example": {
                "en": "His failure has nothing to do with me.",
                "vi": "Sự thất bại của anh ấy không có liên quan gì tới tôi."
            }
        },
        {
            "content": "việc thất bại",
            "type": "",
            "example": {
                "en": "The Dollmaker doesn't tolerate failure.",
                "vi": "The Dollmaker không tha thứ cho việc thất bại đâu."
            }
        },
        {
            "content": "người",
            "type": "pronoun noun",
            "example": {
                "en": "But he could not possibly predict what kind of failure you would become!",
                "vi": "Nhưng ông ấy đã thất bại trong việc dự đoán con người ngươi sẽ trở thành!"
            }
        },
        {
            "content": "phá sản",
            "type": "noun",
            "example": {
                "en": "Although this will be a long process , in my opinion , a significant bank failure is unlikely .",
                "vi": "Mặc dù đây là một tiến trình lâu dài , nhưng tôi nghĩ , ngân hàng phá sản là chuyện không thể xảy ra ."
            }
        },
        {
            "content": "thi trượt",
            "type": "noun",
            "example": {
                "en": "Ousmane’s mother similarly blamed fate for his failure.",
                "vi": "Mẹ của anh Ousmane cũng cho việc anh thi trượt là do số mệnh đã an bài."
            }
        },
        {
            "content": "Thất bại",
            "type": "",
            "example": {
                "en": "His failure has nothing to do with me.",
                "vi": "Sự thất bại của anh ấy không có liên quan gì tới tôi."
            }
        },
        {
            "content": "hỏng hóc",
            "type": "",
            "example": {
                "en": "Telemetry, any chance this is instrumentation failure?",
                "vi": "Tín hiệu, có khi nào là do hỏng hóc thiết bị?"
            }
        }
    ]
}