{
    "word": "fictile",
    "type": [
        "adjective"
    ],
    "us": {
        "hasAudio": 1,
        "phoneticSpelling": [
            "/ˈfiktl/",
            "/ˈfɪktl/",
            "/ˈfikˌtīl/",
            "/ˈfɪkˌtaɪl/"
        ]
    },
    "uk": {
        "hasAudio": 1,
        "phoneticSpelling": [
            "/ˈfɪktʌɪl/",
            "/ˈfɪktɪl/"
        ]
    },
    "meanings": [
        {
            "content": "bằng gốm",
            "type": "",
            "example": {}
        },
        {
            "content": "bằng đất sét",
            "type": "",
            "example": {}
        },
        {
            "content": "nghề đồ gốm",
            "type": "",
            "example": {}
        }
    ]
}