{
    "word": "flavoring",
    "type": [
        "noun",
        "verb"
    ],
    "us": {
        "hasAudio": 1,
        "phoneticSpelling": [
            "/ˈflāvəriNG/",
            "/ˈfleɪvərɪŋ/"
        ]
    },
    "meanings": [
        {
            "content": "hương vị",
            "type": "noun",
            "example": {
                "en": "Explain how salt enhances the flavor of food.",
                "vi": "Giải thích cách thức muối làm tăng hương vị của thức ăn."
            }
        },
        {
            "content": "đồ gia vị",
            "type": "noun",
            "example": {}
        }
    ]
}