{
    "word": "forbearance",
    "type": [
        "noun"
    ],
    "us": {
        "hasAudio": 1,
        "phoneticSpelling": [
            "/fôrˈberəns/",
            "/fɔrˈbɛrəns/",
            "/fərˈberəns/",
            "/fərˈbɛrəns/"
        ]
    },
    "uk": {
        "hasAudio": 1,
        "phoneticSpelling": [
            "/fɔːˈbɛːr(ə)ns/"
        ]
    },
    "meanings": [
        {
            "content": "sự nhịn",
            "type": "noun",
            "example": {}
        },
        {
            "content": "tính chịu đựng",
            "type": "noun",
            "example": {
                "en": "I understand and admire your forbearance.",
                "vi": "Tôi hiểu và ngưỡng mộ tính chịu đựng của anh."
            }
        },
        {
            "content": "tính kiên nhẫn",
            "type": "noun",
            "example": {}
        },
        {
            "content": "kiên trì",
            "type": "",
            "example": {}
        },
        {
            "content": "tự chủ",
            "type": "",
            "example": {}
        }
    ]
}