{
    "word": "glassy",
    "type": [
        "adjective",
        "noun"
    ],
    "us": {
        "hasAudio": 1,
        "phoneticSpelling": [
            "/ˈɡlasē/",
            "/ˈɡlæsi/"
        ]
    },
    "uk": {
        "hasAudio": 1,
        "phoneticSpelling": [
            "/ˈɡlɑːsi/"
        ]
    },
    "meanings": [
        {
            "content": "đờ đẫn",
            "type": "",
            "example": {
                "en": "This is the perfect time to bring back that glassy-eyed look.",
                "vi": "Đây là thời gian thích hợp để đưa trở lại vẻ mặt đờ đẫn."
            }
        },
        {
            "content": "không hồn",
            "type": "",
            "example": {}
        },
        {
            "content": "lờ đờ",
            "type": "adjective",
            "example": {}
        },
        {
            "content": "như thuỷ tinh",
            "type": "",
            "example": {}
        },
        {
            "content": "trong vắt",
            "type": "",
            "example": {}
        },
        {
            "content": "như thủy tinh",
            "type": "adjective",
            "example": {}
        },
        {
            "content": "như gương",
            "type": "",
            "example": {}
        }
    ]
}