{
    "word": "glissade",
    "type": [
        "verb",
        "noun"
    ],
    "us": {
        "hasAudio": 1,
        "phoneticSpelling": [
            "/ɡləˈsäd/",
            "/ɡləˈsɑd/"
        ]
    },
    "uk": {
        "hasAudio": 1,
        "phoneticSpelling": [
            "/ɡlɪˈsɑːd/",
            "/ɡlɪˈseɪd/"
        ]
    },
    "meanings": [
        {
            "content": "bước lướt",
            "type": "",
            "example": {}
        },
        {
            "content": "lướt bước",
            "type": "",
            "example": {}
        },
        {
            "content": "trượt xuống dốc băng",
            "type": "",
            "example": {}
        }
    ]
}