{
    "word": "godless",
    "type": [
        "adjective"
    ],
    "us": {
        "hasAudio": 1,
        "phoneticSpelling": [
            "/ˈɡädləs/",
            "/ˈɡɑdləs/"
        ]
    },
    "uk": {
        "hasAudio": 1,
        "phoneticSpelling": [
            "/ˈɡɒdləs/"
        ]
    },
    "meanings": [
        {
            "content": "không tin thần thánh",
            "type": "",
            "example": {}
        },
        {
            "content": "không tôn giáo",
            "type": "",
            "example": {}
        },
        {
            "content": "trái đạo lý",
            "type": "",
            "example": {}
        },
        {
            "content": "vô thần",
            "type": "",
            "example": {
                "en": "This is the face of the godless madrassa!",
                "vi": "Đây là gương mặt của tên vô thần!"
            }
        },
        {
            "content": "độc ác",
            "type": "",
            "example": {
                "en": "\" And the godless witch was miserably burnt to death. \"",
                "vi": "Và mụ phù thủy độc ác đã bị thiêu sống..."
            }
        }
    ]
}