{
    "word": "helpmeet",
    "type": [
        "noun"
    ],
    "meanings": [
        {
            "content": "bạn đời",
            "type": "",
            "example": {}
        },
        {
            "content": "người cộng tác",
            "type": "",
            "example": {}
        },
        {
            "content": "đồng chí",
            "type": "noun",
            "example": {}
        },
        {
            "content": "đồng sự",
            "type": "",
            "example": {}
        }
    ]
}