{
    "word": "improvisation",
    "type": [
        "noun"
    ],
    "us": {
        "hasAudio": 1,
        "phoneticSpelling": [
            "/imˌprävəˈzāSH(ə)n/",
            "/ɪmˌprɑvəˈzeɪʃ(ə)n/"
        ]
    },
    "uk": {
        "hasAudio": 1,
        "phoneticSpelling": [
            "/ɪmprəvʌɪˈzeɪʃn/"
        ]
    },
    "meanings": [
        {
            "content": "sự ứng biến",
            "type": "",
            "example": {
                "en": "When improvisation, resourcefulness, imagination are key,",
                "vi": "Trong khi sự ứng biến, tháo vát, tưởng tượng là chủ chốt,"
            }
        },
        {
            "content": "khúc tức hứng",
            "type": "",
            "example": {}
        },
        {
            "content": "ngẫu hứng",
            "type": "noun",
            "example": {
                "en": "Bach was like a great improviser with a mind of a chess master.",
                "vi": "Bach là một nhà ngẫu hứng tuyệt vời với một tâm hồn của bậc thầy chơi cờ."
            }
        },
        {
            "content": "sự làm ngay được",
            "type": "",
            "example": {}
        },
        {
            "content": "sự ứng khẩu",
            "type": "",
            "example": {}
        }
    ]
}