{
    "word": "inamorata",
    "type": [
        "noun"
    ],
    "us": {
        "hasAudio": 1,
        "phoneticSpelling": [
            "/iˌnaməˈrädə/",
            "/ɪˌnæməˈrɑdə/"
        ]
    },
    "uk": {
        "hasAudio": 1,
        "phoneticSpelling": [
            "/ɪˌnaməˈrɑːtə/"
        ]
    },
    "meanings": [
        {
            "content": "người yêu",
            "type": "noun",
            "example": {}
        },
        {
            "content": "tình nhân",
            "type": "noun",
            "example": {}
        }
    ]
}