{
    "word": "incommodate",
    "type": [
        "verb"
    ],
    "meanings": [
        {
            "content": "cản tr",
            "type": "",
            "example": {}
        },
        {
            "content": "làm khó chịu",
            "type": "",
            "example": {}
        },
        {
            "content": "làm phiền",
            "type": "",
            "example": {}
        },
        {
            "content": "ngăn trở",
            "type": "",
            "example": {}
        },
        {
            "content": "quấy rầy",
            "type": "verb",
            "example": {}
        }
    ]
}