{
    "word": "intent",
    "type": [
        "adjective",
        "noun"
    ],
    "us": {
        "hasAudio": 1,
        "phoneticSpelling": [
            "/inˈtent/",
            "/ɪnˈtɛnt/"
        ]
    },
    "uk": {
        "hasAudio": 1,
        "phoneticSpelling": [
            "/ɪnˈtɛnt/"
        ]
    },
    "meanings": [
        {
            "content": "chăm chú",
            "type": "",
            "example": {
                "en": "I watched her closely and was surprised that she read every single line—intently.",
                "vi": "Tôi theo dõi bà rất kỹ và ngạc nhiên thấy bà—chăm chú đọc từng hàng chữ."
            }
        },
        {
            "content": "mải mê",
            "type": "",
            "example": {
                "en": "I listened intently, caught up in his explanations.",
                "vi": "Tôi chăm chú lắng nghe, mải mê với những điều anh giải thích."
            }
        },
        {
            "content": "nghĩa",
            "type": "noun",
            "example": {
                "en": "He, for all intents and purposes, is now you.",
                "vi": "Theo 1 nghĩa nào đó thì anh ta giờ chính là anh."
            }
        },
        {
            "content": "hăm hở",
            "type": "",
            "example": {}
        },
        {
            "content": "kiên quyết",
            "type": "adjective",
            "example": {
                "en": "We have good intentions; we start strong; we want to be our best self.",
                "vi": "Chúng ta có ý định tốt; chúng ta bắt đầu với lòng kiên quyết mãnh liệt; chúng ta muốn được làm một người tốt nhất."
            }
        },
        {
            "content": "miệt mài",
            "type": "",
            "example": {}
        },
        {
            "content": "mục đích",
            "type": "noun",
            "example": {
                "en": "But they were of one heart, one mind, and with one intention.",
                "vi": "Nhưng họ đồng tâm nhất trí và có cùng một mục đích."
            }
        },
        {
            "content": "sôi nôi",
            "type": "",
            "example": {}
        },
        {
            "content": "ý định",
            "type": "",
            "example": {
                "en": "Tom had no intention of ever seeing Mary again.",
                "vi": "Tom không có ý định gặp lại Mary nữa."
            }
        },
        {
            "content": "đeo đuổi",
            "type": "",
            "example": {}
        },
        {
            "content": "đầy nhiệt tình",
            "type": "",
            "example": {}
        }
    ]
}