{
    "word": "inwardness",
    "type": [
        "noun"
    ],
    "us": {
        "hasAudio": 1,
        "phoneticSpelling": [
            "/ˈinwərdnəs/",
            "/ˈɪnwərdnəs/"
        ]
    },
    "uk": {
        "hasAudio": 1,
        "phoneticSpelling": [
            "/ˈɪnwədnɪs/"
        ]
    },
    "meanings": [
        {
            "content": "thực chất",
            "type": "",
            "example": {}
        },
        {
            "content": "tính chất ở trong",
            "type": "",
            "example": {}
        },
        {
            "content": "tính sâu sắc",
            "type": "",
            "example": {}
        },
        {
            "content": "ý nghĩ sâu sắc",
            "type": "",
            "example": {}
        }
    ]
}