{
    "word": "jasmine",
    "type": [
        "noun"
    ],
    "us": {
        "hasAudio": 1,
        "phoneticSpelling": [
            "/ˈjazmən/",
            "/ˈdʒæzmən/"
        ]
    },
    "uk": {
        "hasAudio": 1,
        "phoneticSpelling": [
            "/ˈdʒazmɪn/",
            "/ˈdʒasmɪn/"
        ]
    },
    "meanings": [
        {
            "content": "nhài",
            "type": "noun",
            "example": {
                "en": "There was jasmine and...",
                "vi": "Có hoa nhài và..."
            }
        },
        {
            "content": "hoa lài",
            "type": "",
            "example": {
                "en": "A kitchen garden that smells of herbs in the day... jasmine in the evening.",
                "vi": "Một khu vườn thơm ngát hương cây cỏ thảo dược vào ban ngày, và hương hoa lài vào buổi tối."
            }
        },
        {
            "content": "hoa nhài",
            "type": "noun",
            "example": {
                "en": "The slimy cobra slithered toward the girl, lured by the scent of the jasmine flowers in her hair.",
                "vi": "Con rắn hổ mang nhớp nháp trườn về phía cô gái, quyến rũ bởi mùi hương của hoa nhài trong tóc cô."
            }
        },
        {
            "content": "lài",
            "type": "noun",
            "example": {
                "en": "A kitchen garden that smells of herbs in the day... jasmine in the evening.",
                "vi": "Một khu vườn thơm ngát hương cây cỏ thảo dược vào ban ngày, và hương hoa lài vào buổi tối."
            }
        },
        {
            "content": "chi nhài",
            "type": "",
            "example": {}
        },
        {
            "content": "tinh dầu nhài",
            "type": "",
            "example": {}
        }
    ]
}