{
    "word": "troops",
    "type": [
        "verb",
        "noun"
    ],
    "meanings": [
        {
            "content": "quân đội",
            "type": "noun",
            "example": {
                "en": "Tanks and planes may defeat the troops but they cannot conquer the people.",
                "vi": "Xe tăng và máy bay có thể đánh bại quân đội nhưng chúng không thề chinh phục được người dân."
            }
        },
        {
            "content": "binh lính",
            "type": "",
            "example": {
                "en": "I think the troops are trying to tell us something, fellas.",
                "vi": "Tôi nghĩ binh lính đang cho vài ý kiến đấy."
            }
        },
        {
            "content": "binh sĩ",
            "type": "noun",
            "example": {
                "en": "Then we need to double the number of troops guarding the plant.",
                "vi": "Vậy ta cần tăng gấp đôi số lượng binh sĩ bảo vệ cơ sở."
            }
        },
        {
            "content": "giáp sĩ",
            "type": "",
            "example": {}
        },
        {
            "content": "quân lính",
            "type": "noun",
            "example": {
                "en": "She followed the troops to the frontline and died there.",
                "vi": "Cô ấy theo quân lính ra mặt trận và chết rồi."
            }
        },
        {
            "content": "quân mã",
            "type": "",
            "example": {}
        },
        {
            "content": "binh đoàn",
            "type": "noun",
            "example": {
                "en": "Refugees, or troops of soldiers, weapons, maybe bombs!",
                "vi": "Dân tị nạn, hoặc các binh đoàn lính, vũ khí, có thể cả bom!"
            }
        },
        {
            "content": "binh đội",
            "type": "noun",
            "example": {}
        },
        {
            "content": "binh",
            "type": "noun",
            "example": {
                "en": "I think the troops are trying to tell us something, fellas.",
                "vi": "Tôi nghĩ binh lính đang cho vài ý kiến đấy."
            }
        },
        {
            "content": "lính",
            "type": "",
            "example": {
                "en": "She followed the troops to the frontline and died there.",
                "vi": "Cô ấy theo quân lính ra mặt trận và chết rồi."
            }
        },
        {
            "content": "ngũ",
            "type": "numeral",
            "example": {}
        },
        {
            "content": "quân",
            "type": "noun",
            "example": {
                "en": "We can only hope the government decides to withdraw its troops.",
                "vi": "Chúng ta chỉ có thể hy vọng rằng chính phủ quyết định rút quân."
            }
        }
    ]
}