{
    "word": "ulna",
    "type": [
        "noun"
    ],
    "us": {
        "hasAudio": 1,
        "phoneticSpelling": [
            "/ˈəlnə/"
        ]
    },
    "uk": {
        "hasAudio": 1,
        "phoneticSpelling": [
            "/ˈʌlnə/"
        ]
    },
    "meanings": [
        {
            "content": "xương trụ",
            "type": "noun",
            "example": {}
        },
        {
            "content": "Xương trụ",
            "type": "",
            "example": {}
        }
    ]
}