{
    "word": "unconsecrated",
    "type": [
        "adjective"
    ],
    "uk": {
        "hasAudio": 1,
        "phoneticSpelling": [
            "/ʌnˈkɒnsɪkreɪtɪd/"
        ]
    },
    "meanings": [
        {
            "content": "không được hiến dâng",
            "type": "",
            "example": {}
        },
        {
            "content": "không được phong",
            "type": "",
            "example": {}
        },
        {
            "content": "không được thờ cúng",
            "type": "",
            "example": {}
        },
        {
            "content": "không được tôn",
            "type": "",
            "example": {}
        },
        {
            "content": "không được đem dâng",
            "type": "",
            "example": {}
        }
    ]
}