{
    "word": "unhusk",
    "type": [
        "verb"
    ],
    "us": {
        "hasAudio": 1,
        "phoneticSpelling": [
            "/ˌənˈhəsk/"
        ]
    },
    "uk": {
        "hasAudio": 1,
        "phoneticSpelling": [
            "/ʌnˈhʌsk/"
        ]
    },
    "meanings": [
        {
            "content": "xây",
            "type": "",
            "example": {}
        },
        {
            "content": "bóc vỏ",
            "type": "",
            "example": {}
        },
        {
            "content": "lột vỏ",
            "type": "",
            "example": {}
        }
    ]
}