{
    "word": "unpriestly",
    "type": [
        "adjective"
    ],
    "us": {
        "hasAudio": 0,
        "phoneticSpelling": [
            "/(ˌ)ʌnˈpriːs(t)li/"
        ]
    },
    "uk": {
        "hasAudio": 0,
        "phoneticSpelling": [
            "/(ˌ)ʌnˈpriːs(t)li/"
        ]
    },
    "meanings": [
        {
            "content": "không giống thầy tu",
            "type": "",
            "example": {}
        },
        {
            "content": "không giống thầy tế",
            "type": "",
            "example": {}
        }
    ]
}