{
    "word": "verbena",
    "type": [
        "noun"
    ],
    "us": {
        "hasAudio": 1,
        "phoneticSpelling": [
            "/vərˈbēnə/",
            "/vərˈbinə/"
        ]
    },
    "uk": {
        "hasAudio": 1,
        "phoneticSpelling": [
            "/vəːˈbiːnə/"
        ]
    },
    "meanings": [
        {
            "content": "cỏ roi ngựa",
            "type": "",
            "example": {}
        },
        {
            "content": "chi cỏ roi ngựa",
            "type": "",
            "example": {}
        }
    ]
}