{
    "word": "warhead",
    "type": [
        "noun"
    ],
    "us": {
        "hasAudio": 1,
        "phoneticSpelling": [
            "/ˈwôrˌhed/",
            "/ˈwɔrˌhɛd/"
        ]
    },
    "uk": {
        "hasAudio": 1,
        "phoneticSpelling": [
            "/ˈwɔːhɛd/"
        ]
    },
    "meanings": [
        {
            "content": "đầu đạn",
            "type": "noun",
            "example": {
                "en": "Prep the warheads and get them moving to the coast.",
                "vi": "Chuẩn bị đầu đạn và đưa chúng ra bờ biển."
            }
        }
    ]
}